ttgc/__init__.py
ttgc/globals.py
ttgc/helpers.py
ttgc/initialize.py
ttgc/landmark.py
ttgc/plotting.py
ttgc/run_sim.py
ttgc/update.py
ttgc-1.1.0.dist-info/licenses/LICENSE
ttgc-1.1.0.dist-info/METADATA
ttgc-1.1.0.dist-info/WHEEL
ttgc-1.1.0.dist-info/top_level.txt
ttgc-1.1.0.dist-info/RECORD
