Metadata-Version: 2.4
Name: ttgc
Version: 1.1.0
Summary: A twisted torus model of grid cell activity.
Author: John Wen
License-Expression: GPL-3.0-or-later
Project-URL: Repository, https://github.com/johnhwen1/ttgc
Keywords: grid cell,twisted torus,topology
Classifier: Programming Language :: Python :: 3
Requires-Python: >=3.9
License-File: LICENSE
Requires-Dist: numpy
Requires-Dist: matplotlib
Requires-Dist: scipy
Requires-Dist: GPUtil
Dynamic: license-file
